dj_database_url/__init__.py
dj_database_url/py.typed
dj_database_url-2.2.0.dist-info/LICENSE
dj_database_url-2.2.0.dist-info/METADATA
dj_database_url-2.2.0.dist-info/WHEEL
dj_database_url-2.2.0.dist-info/top_level.txt
dj_database_url-2.2.0.dist-info/RECORD
