Metadata-Version: 2.1
Name: dj-database-url
Version: 2.2.0
Summary: Use Database URLs in your Django Application.
Home-page: https://github.com/jazzband/dj-database-url
Author: Original Author: Kenneth Reitz, Maintained by: JazzBand Community
License: BSD
Project-URL: GitHub, https://github.com/jazzband/dj-database-url/
Project-URL: Release log, https://github.com/jazzband/dj-database-url/blob/master/CHANGELOG.md
Platform: any
Classifier: Environment :: Web Environment
Classifier: Framework :: Django
Classifier: Framework :: Django :: 3.2
Classifier: Framework :: Django :: 4.2
Classifier: Framework :: Django :: 5.0
Classifier: Intended Audience :: Developers
Classifier: License :: OSI Approved :: BSD License
Classifier: Operating System :: OS Independent
Classifier: Programming Language :: Python
Classifier: Topic :: Internet :: WWW/HTTP :: Dynamic Content
Classifier: Topic :: Software Development :: Libraries :: Python Modules
Classifier: Programming Language :: Python
Classifier: Programming Language :: Python :: 3
Classifier: Programming Language :: Python :: 3.7
Classifier: Programming Language :: Python :: 3.8
Classifier: Programming Language :: Python :: 3.9
Classifier: Programming Language :: Python :: 3.10
Classifier: Programming Language :: Python :: 3.11
Classifier: Programming Language :: Python :: 3.12
License-File: LICENSE
Requires-Dist: Django>=3.2
Requires-Dist: typing_extensions>=3.10.0.0
